dbapi_mongodb-0.1.1.dist-info/licenses/LICENSE
mongo_dbapi/__init__.py
mongo_dbapi/async_dbapi.py
mongo_dbapi/dbapi.py
mongo_dbapi/errors.py
mongo_dbapi/sqlalchemy_dialect.py
mongo_dbapi/translation.py
dbapi_mongodb-0.1.1.dist-info/METADATA
dbapi_mongodb-0.1.1.dist-info/WHEEL
dbapi_mongodb-0.1.1.dist-info/top_level.txt
dbapi_mongodb-0.1.1.dist-info/RECORD
