Metadata-Version: 2.4
Name: dbapi-mongodb
Version: 0.1.1
Summary: DBAPI-style adapter that translates SQL (JOIN/DDL/aggregations) into MongoDB operations
Requires-Python: >=3.10
License-File: LICENSE
Requires-Dist: pymongo<4.0,>=3.13
Requires-Dist: sqlglot>=25.7.0
Provides-Extra: dev
Requires-Dist: pytest>=8.3.0; extra == "dev"
Requires-Dist: sqlalchemy>=2.0.0; extra == "dev"
Dynamic: license-file
